heartwave/__init__.py
heartwave/app.py
heartwave/conf.py
heartwave/facetracker.py
heartwave/person.py
heartwave/plot.py
heartwave/sceneanalyzer.py
heartwave/util.py
heartwave/videostream.py
heartwave/widgets.py
heartwave/data/lbpcascade_frontalface_improved.xml
heartwave-0.9.2.dist-info/LICENSE
heartwave-0.9.2.dist-info/METADATA
heartwave-0.9.2.dist-info/WHEEL
heartwave-0.9.2.dist-info/entry_points.txt
heartwave-0.9.2.dist-info/top_level.txt
heartwave-0.9.2.dist-info/RECORD
